{
  "recentFiles": [
    {
      "basename": "Chapter 7",
      "path": "Computing+/Chapter 7.md"
    },
    {
      "basename": "Essay Thinking Pages",
      "path": "History/Essay Thinking Pages/Essay Thinking Pages.md"
    },
    {
      "basename": "What can y",
      "path": "History/Essay Thinking Pages/What can y.md"
    },
    {
      "basename": "Notes",
      "path": "History/Notes/Notes.md"
    },
    {
      "basename": "Facism vs Nazism",
      "path": "History/Notes/Hitler/Facism vs Nazism.md"
    },
    {
      "basename": "Social Studies",
      "path": "Social Studies/Social Studies.md"
    },
    {
      "basename": "Chapter 11",
      "path": "Computing+/Chapter 11.md"
    },
    {
      "basename": "Key principles",
      "path": "Social Studies/Key principles.md"
    },
    {
      "basename": "Chapter 7 2022-04-10 16.46.56.excalidraw",
      "path": "Chapter 7 2022-04-10 16.46.56.excalidraw.md"
    },
    {
      "basename": "Sharing From 2021 Alumni",
      "path": "Computing+/Sharing From 2021 Alumni.md"
    },
    {
      "basename": "Chapter 6.1",
      "path": "Computing+/Chapter 6.1.md"
    },
    {
      "basename": "Computing+",
      "path": "Computing+/Computing+.md"
    },
    {
      "basename": "English",
      "path": "English/English.md"
    },
    {
      "basename": "Biases",
      "path": "English/Biases.md"
    },
    {
      "basename": "SBQ",
      "path": "History/SBQ/SBQ.md"
    },
    {
      "basename": "Reliability",
      "path": "History/SBQ/Reliability.md"
    },
    {
      "basename": "SEQ",
      "path": "History/SEQ/SEQ.md"
    },
    {
      "basename": "Explanation",
      "path": "History/SEQ/Explanation/Explanation.md"
    },
    {
      "basename": "Weimar republic",
      "path": "History/Notes/Hitler/Weimar republic/Weimar republic.md"
    },
    {
      "basename": "The Rise of Hitler",
      "path": "History/Notes/Hitler/The Rise of Hitler/The Rise of Hitler.md"
    },
    {
      "basename": "Hitler's impact",
      "path": "History/Notes/Hitler/Hitler's impact/Hitler's impact.md"
    },
    {
      "basename": "Nazi party",
      "path": "History/Notes/Hitler/Nazi party.md"
    },
    {
      "basename": "Chancellor to Dictator",
      "path": "History/Notes/Hitler/Chancellor to Dictator.md"
    },
    {
      "basename": "Hitler",
      "path": "History/Notes/Hitler/Hitler.md"
    },
    {
      "basename": "Globalisation",
      "path": "Social Studies/Globalisation.md"
    },
    {
      "basename": "Evaluation",
      "path": "History/SEQ/Evaluation.md"
    },
    {
      "basename": "Screenshot_2021-03-01_at_9.25.30_AM",
      "path": "History/SEQ/Explanation/Screenshot_2021-03-01_at_9.25.30_AM.png"
    },
    {
      "basename": "Assertion",
      "path": "Social Studies/SBQ/Assertion.md"
    },
    {
      "basename": "Surprise",
      "path": "Social Studies/SBQ/Surprise.md"
    },
    {
      "basename": "Comparison",
      "path": "Social Studies/SBQ/Comparison.md"
    },
    {
      "basename": "Chinese",
      "path": "Chinese/Chinese.md"
    },
    {
      "basename": "WWII (Part 2)",
      "path": "History/Notes/WWII (Part 2)/WWII (Part 2).md"
    },
    {
      "basename": "WWII",
      "path": "History/Notes/WWII/WWII.md"
    },
    {
      "basename": "Nazi-Soviet Pact",
      "path": "History/Notes/WWII/Nazi-Soviet Pact.md"
    },
    {
      "basename": "Invasion of Abyssinia",
      "path": "History/Notes/WWII/Invasion of Abyssinia.md"
    },
    {
      "basename": "Hitler’s Expansionist Foreign Policy",
      "path": "History/Notes/WWII/Hitler’s Expansionist Foreign Policy.md"
    },
    {
      "basename": "Breaking of WWII",
      "path": "History/Notes/WWII/Breaking of WWII.md"
    },
    {
      "basename": "Appeasement Policy",
      "path": "History/Notes/WWII/Appeasement Policy.md"
    },
    {
      "basename": "Rise of Mussolini",
      "path": "History/Notes/WWII/Rise of Mussolini.md"
    },
    {
      "basename": "Weaknesses of the League",
      "path": "History/Notes/WWII/Weaknesses of the League.md"
    },
    {
      "basename": "Military Japan",
      "path": "History/Notes/Military Japan/Military Japan.md"
    },
    {
      "basename": "WWI",
      "path": "History/Notes/WWI/WWI.md"
    },
    {
      "basename": "League of Nations",
      "path": "History/Notes/WWI/League of Nations.md"
    },
    {
      "basename": "Propaganda",
      "path": "History/Notes/Hitler/The Rise of Hitler/Propaganda.md"
    },
    {
      "basename": "Untitled 1",
      "path": "History/Notes/Hitler/Weimar republic/Untitled 1.png"
    },
    {
      "basename": "Untitled",
      "path": "History/Notes/Hitler/Weimar republic/Untitled.png"
    },
    {
      "basename": "Screenshot_2021-10-08_at_3.25.00_PM",
      "path": "History/Notes/Hitler/The Rise of Hitler/Screenshot_2021-10-08_at_3.25.00_PM.png"
    },
    {
      "basename": "Screenshot_2021-09-30_at_2.59.34_PM",
      "path": "History/Notes/Hitler/Hitler's impact/Screenshot_2021-09-30_at_2.59.34_PM.png"
    },
    {
      "basename": "Stalin",
      "path": "History/Notes/Stalin/Stalin.md"
    },
    {
      "basename": "Communism v Capitalism v Socialism",
      "path": "History/Notes/Stalin/Communism v Capitalism v Socialism.md"
    }
  ],
  "omittedPaths": [],
  "maxLength": null
}